MANIFEST.in
README.md
ballerina.py
ballerina_aws_helper.py
setup.py
version.py
athena_ballerina.egg-info/PKG-INFO
athena_ballerina.egg-info/SOURCES.txt
athena_ballerina.egg-info/dependency_links.txt
athena_ballerina.egg-info/entry_points.txt
athena_ballerina.egg-info/requires.txt
athena_ballerina.egg-info/top_level.txt