Metadata-Version: 2.1
Name: athena-ballerina
Version: 0.0.6
Summary: SQL migrations for AWS Athena
Home-page: https://github.com/leantaas/athena-ballerina
Author: ae
Author-email: opensource@leantaas.com
License: Apache License 2.0
Platform: UNKNOWN
Classifier: License :: OSI Approved :: Apache Software License
Classifier: Programming Language :: Python
Classifier: Programming Language :: Python :: 3
Classifier: Programming Language :: Python :: 3.6
Classifier: Programming Language :: Python :: Implementation :: CPython
Requires-Python: >=3.6.0
